objname/__init__.py
objname/_module.py
objname/bench_objname.py
objname/py.typed
objname/test_objname.py
objname-0.12.1.dist-info/LICENSE
objname-0.12.1.dist-info/METADATA
objname-0.12.1.dist-info/WHEEL
objname-0.12.1.dist-info/top_level.txt
objname-0.12.1.dist-info/RECORD
