Metadata-Version: 2.1
Name: objname
Version: 0.12.1
Summary: A library with a base class that stores the assigned name of an object.
Home-page: https://github.com/AlanCristhian/objname
Author: Alan Cristhian Ruiz
Author-email: alan.cristh@gmail.com
License: MIT
Keywords: data structure debug
Classifier: Development Status :: 2 - Pre-Alpha
Classifier: Intended Audience :: Developers
Classifier: License :: OSI Approved :: MIT License
Classifier: Programming Language :: Python :: 3.6
Classifier: Programming Language :: Python :: 3.7
Classifier: Programming Language :: Python :: 3.8
Classifier: Programming Language :: Python :: 3.9
Classifier: Programming Language :: Python :: 3.10
Classifier: Programming Language :: Python :: 3.11
Classifier: Programming Language :: Python :: Implementation :: CPython
Classifier: Programming Language :: Python :: Implementation :: PyPy
Classifier: Topic :: Software Development
Classifier: Topic :: Software Development :: Object Brokering
Classifier: Typing :: Typed
License-File: LICENSE
